DataCollector/DataCollector.py
DataCollector/__init__.py
DataCollector/NBA/NbaDataCollectorLibrary.py
DataCollector/NBA/__init__.py
DataCollector/NBA/PlayerRawStats/PlayerRawStats.py
DataCollector/NBA/PlayerRawStats/__init__.py
SportStatIQ_DataCollectors-1.0.3.dist-info/METADATA
SportStatIQ_DataCollectors-1.0.3.dist-info/WHEEL
SportStatIQ_DataCollectors-1.0.3.dist-info/top_level.txt
SportStatIQ_DataCollectors-1.0.3.dist-info/RECORD
