Metadata-Version: 2.1
Name: SportStatIQ-DataCollectors
Version: 1.0.3
Summary: Collects data from various sports websites
Home-page: https://github.com/SportStatIQ/SportStatIQ-DataCollectors
Author: Matthew Myrick
Author-email: MatthewMyrick2@gmail.com
License: MIT
Classifier: Development Status :: 3 - Alpha
Classifier: Intended Audience :: Developers
Classifier: License :: OSI Approved :: MIT License
Classifier: Operating System :: OS Independent
Classifier: Programming Language :: Python
Classifier: Programming Language :: Python :: 3
Classifier: Programming Language :: Python :: 3.7
Classifier: Programming Language :: Python :: 3.8
Classifier: Programming Language :: Python :: 3.9
Classifier: Topic :: Software Development :: Libraries
Classifier: Topic :: Utilities
Requires-Dist: pandas
Requires-Dist: requests
Requires-Dist: bs4
